client/__init__.py
client/add_contact.py
client/chat_window.py
client/database.py
client/delete_contact.py
client/start_conversation.py
client/transport.py
client/ui_client.py
common/__init__.py
common/decorators.py
common/descriptor.py
common/errors.py
common/metaclasses.py
common/utils.py
common/variables.py
doc_project/__init__.py
doc_project/source/__init__.py
doc_project/source/conf.py
project_logs/__init__.py
project_logs/configs/__init__.py
project_logs/configs/config_client_log.py
project_logs/configs/config_server_log.py
unit_tests/__init__.py
mess_client_anna-0.0.1.dist-info/METADATA
mess_client_anna-0.0.1.dist-info/WHEEL
mess_client_anna-0.0.1.dist-info/top_level.txt
mess_client_anna-0.0.1.dist-info/RECORD
